JATA/CJH/CJH.py
JATA/CJH/__init__.py
JATA/DV/DV.py
JATA/DV/__init__.py
JATA/Helpers/Helpers.py
JATA/Helpers/__init__.py
JATA/LOEB/LOEB.py
JATA/LOEB/__init__.py
JATA/Text/Text.py
JATA/Text/__init__.py
JATA/UpdatedPixPlot/UpdatedPixPlot.py
JATA/UpdatedPixPlot/__init__.py
JATATools-0.2.1.dist-info/LICENSE
JATATools-0.2.1.dist-info/METADATA
JATATools-0.2.1.dist-info/WHEEL
JATATools-0.2.1.dist-info/top_level.txt
JATATools-0.2.1.dist-info/RECORD
