Metadata-Version: 2.1
Name: JATATools
Version: 0.2.1
Summary: A Digital Humanities Package
Home-page: https://github.com/albisbub/JATA-TOOLS
Author: Blaise Albis Burdige
Author-email: albisbub@reed.edu
License: UNKNOWN
Platform: UNKNOWN
Classifier: Programming Language :: Python :: 3
Classifier: License :: OSI Approved :: MIT License
Classifier: Operating System :: OS Independent
Requires-Python: >=3.6
